{
  "version": "2026-04-09",
  "source": "Project-maintained battery catalog for hybrid sizing (datasheet-backed current/energy checks) + BYD HVS/LVS, Dyness DL5.0C, Sungrow SBR datasheet expansion",
  "batteries": [
    {
      "id": "byd_hvs_10_2",
      "manufacturer": "BYD",
      "model": "Battery-Box Premium HVS 10.2",
      "chemistry": "lifepo4",
      "nominalV": 409.6,
      "capacityAh": 25.0,
      "recommendedDod": 0.95,
      "continuousCharge_A": 25.0,
      "continuousDischarge_A": 25.0,
      "peakDischarge_A": 50.0,
      "peakDuration_s": 3.0,
      "tempMinC": -10.0,
      "tempMaxC": 50.0,
      "datasheetRev": "HVS V1.4 (2024-12)",
      "datasheetUrl": "https://bydbatterybox.com/uploads/downloads/241212_Datasheet_Battery-Box%20HVS_V1.4_EN-675a34b4e7bfb.pdf",
      "note": "4 modules, 10.24kWh usable."
    },
    {
      "id": "byd_hvs_12_8",
      "manufacturer": "BYD",
      "model": "Battery-Box Premium HVS 12.8",
      "chemistry": "lifepo4",
      "nominalV": 512.0,
      "capacityAh": 25.0,
      "recommendedDod": 0.95,
      "continuousCharge_A": 25.0,
      "continuousDischarge_A": 25.0,
      "peakDischarge_A": 50.0,
      "peakDuration_s": 3.0,
      "tempMinC": -10.0,
      "tempMaxC": 50.0,
      "datasheetRev": "HVS V1.4 (2024-12)",
      "datasheetUrl": "https://bydbatterybox.com/uploads/downloads/241212_Datasheet_Battery-Box%20HVS_V1.4_EN-675a34b4e7bfb.pdf",
      "note": "5 modules, 12.8kWh usable."
    },
    {
      "id": "byd_hvs_5_1",
      "manufacturer": "BYD",
      "model": "Battery-Box Premium HVS 5.1",
      "chemistry": "lifepo4",
      "nominalV": 204.8,
      "capacityAh": 25.0,
      "recommendedDod": 0.95,
      "continuousCharge_A": 25.0,
      "continuousDischarge_A": 25.0,
      "peakDischarge_A": 50.0,
      "peakDuration_s": 3.0,
      "tempMinC": -10.0,
      "tempMaxC": 50.0,
      "datasheetRev": "HVS V1.4 (2024-12)",
      "datasheetUrl": "https://bydbatterybox.com/uploads/downloads/241212_Datasheet_Battery-Box%20HVS_V1.4_EN-675a34b4e7bfb.pdf",
      "note": "2 modules, 5.12kWh usable."
    },
    {
      "id": "byd_hvs_7_7",
      "manufacturer": "BYD",
      "model": "Battery-Box Premium HVS 7.7",
      "chemistry": "lifepo4",
      "nominalV": 307.2,
      "capacityAh": 25.0,
      "recommendedDod": 0.95,
      "continuousCharge_A": 25.0,
      "continuousDischarge_A": 25.0,
      "peakDischarge_A": 50.0,
      "peakDuration_s": 3.0,
      "tempMinC": -10.0,
      "tempMaxC": 50.0,
      "datasheetRev": "HVS V1.4 (2024-12)",
      "datasheetUrl": "https://bydbatterybox.com/uploads/downloads/241212_Datasheet_Battery-Box%20HVS_V1.4_EN-675a34b4e7bfb.pdf",
      "note": "3 modules, 7.68kWh usable."
    },
    {
      "id": "byd_lvs_12_0",
      "manufacturer": "BYD",
      "model": "Battery-Box Premium LVS 12.0",
      "chemistry": "lifepo4",
      "nominalV": 51.2,
      "capacityAh": 234.375,
      "recommendedDod": 0.95,
      "continuousCharge_A": 195.0,
      "continuousDischarge_A": 195.0,
      "peakDischarge_A": 270.0,
      "peakDuration_s": 5.0,
      "tempMinC": -10.0,
      "tempMaxC": 50.0,
      "datasheetRev": "LVS AU V1.1",
      "datasheetUrl": "https://www.bydbatterybox.com/uploads/downloads/Datasheet%20BYD%20Premium%20LVS%204.0-24.0%20AU%20V1.1-5f977de8ed8ce.pdf",
      "note": "Three-module tower."
    },
    {
      "id": "byd_lvs_16_0",
      "manufacturer": "BYD",
      "model": "Battery-Box Premium LVS 16.0",
      "chemistry": "lifepo4",
      "nominalV": 51.2,
      "capacityAh": 312.5,
      "recommendedDod": 0.95,
      "continuousCharge_A": 250.0,
      "continuousDischarge_A": 250.0,
      "peakDischarge_A": 360.0,
      "peakDuration_s": 5.0,
      "tempMinC": -10.0,
      "tempMaxC": 50.0,
      "datasheetRev": "LVS AU V1.1",
      "datasheetUrl": "https://www.bydbatterybox.com/uploads/downloads/Datasheet%20BYD%20Premium%20LVS%204.0-24.0%20AU%20V1.1-5f977de8ed8ce.pdf",
      "note": "Four-module tower."
    },
    {
      "id": "byd_lvs_20_0",
      "manufacturer": "BYD",
      "model": "Battery-Box Premium LVS 20.0",
      "chemistry": "lifepo4",
      "nominalV": 51.2,
      "capacityAh": 390.625,
      "recommendedDod": 0.95,
      "continuousCharge_A": 250.0,
      "continuousDischarge_A": 250.0,
      "peakDischarge_A": 360.0,
      "peakDuration_s": 5.0,
      "tempMinC": -10.0,
      "tempMaxC": 50.0,
      "datasheetRev": "LVS AU V1.1",
      "datasheetUrl": "https://www.bydbatterybox.com/uploads/downloads/Datasheet%20BYD%20Premium%20LVS%204.0-24.0%20AU%20V1.1-5f977de8ed8ce.pdf",
      "note": "Five-module tower (single-tower only in datasheet)."
    },
    {
      "id": "byd_lvs_24_0",
      "manufacturer": "BYD",
      "model": "Battery-Box Premium LVS 24.0",
      "chemistry": "lifepo4",
      "nominalV": 51.2,
      "capacityAh": 468.75,
      "recommendedDod": 0.95,
      "continuousCharge_A": 250.0,
      "continuousDischarge_A": 250.0,
      "peakDischarge_A": 360.0,
      "peakDuration_s": 5.0,
      "tempMinC": -10.0,
      "tempMaxC": 50.0,
      "datasheetRev": "LVS AU V1.1",
      "datasheetUrl": "https://www.bydbatterybox.com/uploads/downloads/Datasheet%20BYD%20Premium%20LVS%204.0-24.0%20AU%20V1.1-5f977de8ed8ce.pdf",
      "note": "Six-module tower (single-tower only in datasheet)."
    },
    {
      "id": "byd_lvs_4_0",
      "manufacturer": "BYD",
      "model": "Battery-Box Premium LVS 4.0",
      "chemistry": "lifepo4",
      "nominalV": 51.2,
      "capacityAh": 78.125,
      "recommendedDod": 0.95,
      "continuousCharge_A": 65.0,
      "continuousDischarge_A": 65.0,
      "peakDischarge_A": 90.0,
      "peakDuration_s": 5.0,
      "tempMinC": -10.0,
      "tempMaxC": 50.0,
      "datasheetRev": "LVS AU V1.1",
      "datasheetUrl": "https://www.bydbatterybox.com/uploads/downloads/Datasheet%20BYD%20Premium%20LVS%204.0-24.0%20AU%20V1.1-5f977de8ed8ce.pdf",
      "note": "Single module tower."
    },
    {
      "id": "byd_lvs_8_0",
      "manufacturer": "BYD",
      "model": "Battery-Box Premium LVS 8.0",
      "chemistry": "lifepo4",
      "nominalV": 51.2,
      "capacityAh": 156.25,
      "recommendedDod": 0.95,
      "continuousCharge_A": 130.0,
      "continuousDischarge_A": 130.0,
      "peakDischarge_A": 180.0,
      "peakDuration_s": 5.0,
      "tempMinC": -10.0,
      "tempMaxC": 50.0,
      "datasheetRev": "LVS AU V1.1",
      "datasheetUrl": "https://www.bydbatterybox.com/uploads/downloads/Datasheet%20BYD%20Premium%20LVS%204.0-24.0%20AU%20V1.1-5f977de8ed8ce.pdf",
      "note": "Two-module tower."
    },
    {
      "id": "dyness_bx51100",
      "manufacturer": "Dyness",
      "model": "BX51100",
      "chemistry": "lifepo4",
      "nominalV": 51.2,
      "capacityAh": 100.0,
      "recommendedDod": 0.9,
      "continuousCharge_A": 50.0,
      "continuousDischarge_A": 75.0,
      "peakDischarge_A": 100.0,
      "peakDuration_s": 10.0,
      "tempMinC": 0.0,
      "tempMaxC": 50.0,
      "datasheetRev": "BX51100 (engineering reference)",
      "datasheetUrl": "",
      "note": "Nominal 5.12kWh module."
    },
    {
      "id": "dyness_dl5_0c",
      "manufacturer": "Dyness",
      "model": "DL5.0C",
      "chemistry": "lifepo4",
      "nominalV": 51.2,
      "capacityAh": 100.0,
      "recommendedDod": 0.9,
      "continuousCharge_A": 50.0,
      "continuousDischarge_A": 75.0,
      "peakDischarge_A": 110.0,
      "peakDuration_s": 15.0,
      "tempMinC": -20.0,
      "tempMaxC": 55.0,
      "datasheetRev": "DL5.0C V1.0-20241011",
      "datasheetUrl": "https://dyness.com/Public/Uploads/uploadfile/files/20241016/DynessDL5.0CdatasheetEN.pdf",
      "note": "Charge temp 0..55C, discharge temp -20..55C. Pack min/max set to full operating envelope."
    },
    {
      "id": "narada_48npfc100",
      "manufacturer": "Narada",
      "model": "48NPFC100",
      "chemistry": "lifepo4",
      "nominalV": 51.2,
      "capacityAh": 100.0,
      "recommendedDod": 0.9,
      "continuousCharge_A": 50.0,
      "continuousDischarge_A": 100.0,
      "peakDischarge_A": 120.0,
      "peakDuration_s": 10.0,
      "tempMinC": 0.0,
      "tempMaxC": 50.0,
      "datasheetRev": "48NPFC100 (engineering reference)",
      "datasheetUrl": "",
      "note": "Nominal 5.12kWh rack battery."
    },
    {
      "id": "pylontech_us5000",
      "manufacturer": "Pylontech",
      "model": "US5000",
      "chemistry": "lifepo4",
      "nominalV": 48.0,
      "capacityAh": 100.0,
      "recommendedDod": 0.95,
      "continuousCharge_A": 50.0,
      "continuousDischarge_A": 100.0,
      "peakDischarge_A": 120.0,
      "peakDuration_s": 15.0,
      "tempMinC": 0.0,
      "tempMaxC": 50.0,
      "datasheetRev": "US5000 (engineering reference)",
      "datasheetUrl": "",
      "note": "Nominal 4.8kWh module."
    },
    {
      "id": "sungrow_sbr064",
      "manufacturer": "Sungrow",
      "model": "SBR064",
      "chemistry": "lifepo4",
      "nominalV": 128.0,
      "capacityAh": 50.0,
      "recommendedDod": 1.0,
      "continuousCharge_A": 30.0,
      "continuousDischarge_A": 30.0,
      "peakDischarge_A": 30.0,
      "peakDuration_s": 0.0,
      "tempMinC": -20.0,
      "tempMaxC": 50.0,
      "datasheetRev": "SBR V5 (2024-09)",
      "datasheetUrl": "https://info-support.sungrowpower.com/application/pdf/2024/09/13/DS_20240907_SBR064_096_128_160_192_224_256_Datasheet_V5_EN.pdf",
      "note": "2 modules (6.4kWh). Some inverter families may cap SBR064 current lower; verify compatibility sheet."
    },
    {
      "id": "sungrow_sbr096",
      "manufacturer": "Sungrow",
      "model": "SBR096",
      "chemistry": "lifepo4",
      "nominalV": 192.0,
      "capacityAh": 50.0,
      "recommendedDod": 1.0,
      "continuousCharge_A": 30.0,
      "continuousDischarge_A": 30.0,
      "peakDischarge_A": 30.0,
      "peakDuration_s": 0.0,
      "tempMinC": -20.0,
      "tempMaxC": 50.0,
      "datasheetRev": "SBR V5 (2024-09)",
      "datasheetUrl": "https://info-support.sungrowpower.com/application/pdf/2024/09/13/DS_20240907_SBR064_096_128_160_192_224_256_Datasheet_V5_EN.pdf",
      "note": "3 modules (9.6kWh)."
    },
    {
      "id": "sungrow_sbr128",
      "manufacturer": "Sungrow",
      "model": "SBR128",
      "chemistry": "lifepo4",
      "nominalV": 256.0,
      "capacityAh": 50.0,
      "recommendedDod": 1.0,
      "continuousCharge_A": 30.0,
      "continuousDischarge_A": 30.0,
      "peakDischarge_A": 30.0,
      "peakDuration_s": 0.0,
      "tempMinC": -20.0,
      "tempMaxC": 50.0,
      "datasheetRev": "SBR V5 (2024-09)",
      "datasheetUrl": "https://info-support.sungrowpower.com/application/pdf/2024/09/13/DS_20240907_SBR064_096_128_160_192_224_256_Datasheet_V5_EN.pdf",
      "note": "4 modules (12.8kWh)."
    },
    {
      "id": "sungrow_sbr160",
      "manufacturer": "Sungrow",
      "model": "SBR160",
      "chemistry": "lifepo4",
      "nominalV": 320.0,
      "capacityAh": 50.0,
      "recommendedDod": 1.0,
      "continuousCharge_A": 30.0,
      "continuousDischarge_A": 30.0,
      "peakDischarge_A": 30.0,
      "peakDuration_s": 0.0,
      "tempMinC": -20.0,
      "tempMaxC": 50.0,
      "datasheetRev": "SBR V5 (2024-09)",
      "datasheetUrl": "https://info-support.sungrowpower.com/application/pdf/2024/09/13/DS_20240907_SBR064_096_128_160_192_224_256_Datasheet_V5_EN.pdf",
      "note": "5 modules (16.0kWh)."
    },
    {
      "id": "sungrow_sbr192",
      "manufacturer": "Sungrow",
      "model": "SBR192",
      "chemistry": "lifepo4",
      "nominalV": 384.0,
      "capacityAh": 50.0,
      "recommendedDod": 1.0,
      "continuousCharge_A": 30.0,
      "continuousDischarge_A": 30.0,
      "peakDischarge_A": 30.0,
      "peakDuration_s": 0.0,
      "tempMinC": -20.0,
      "tempMaxC": 50.0,
      "datasheetRev": "SBR V5 (2024-09)",
      "datasheetUrl": "https://info-support.sungrowpower.com/application/pdf/2024/09/13/DS_20240907_SBR064_096_128_160_192_224_256_Datasheet_V5_EN.pdf",
      "note": "6 modules (19.2kWh)."
    },
    {
      "id": "sungrow_sbr224",
      "manufacturer": "Sungrow",
      "model": "SBR224",
      "chemistry": "lifepo4",
      "nominalV": 448.0,
      "capacityAh": 50.0,
      "recommendedDod": 1.0,
      "continuousCharge_A": 30.0,
      "continuousDischarge_A": 30.0,
      "peakDischarge_A": 30.0,
      "peakDuration_s": 0.0,
      "tempMinC": -20.0,
      "tempMaxC": 50.0,
      "datasheetRev": "SBR V5 (2024-09)",
      "datasheetUrl": "https://info-support.sungrowpower.com/application/pdf/2024/09/13/DS_20240907_SBR064_096_128_160_192_224_256_Datasheet_V5_EN.pdf",
      "note": "7 modules (22.4kWh)."
    },
    {
      "id": "sungrow_sbr256",
      "manufacturer": "Sungrow",
      "model": "SBR256",
      "chemistry": "lifepo4",
      "nominalV": 512.0,
      "capacityAh": 50.0,
      "recommendedDod": 1.0,
      "continuousCharge_A": 30.0,
      "continuousDischarge_A": 30.0,
      "peakDischarge_A": 30.0,
      "peakDuration_s": 0.0,
      "tempMinC": -20.0,
      "tempMaxC": 50.0,
      "datasheetRev": "SBR V5 (2024-09)",
      "datasheetUrl": "https://info-support.sungrowpower.com/application/pdf/2024/09/13/DS_20240907_SBR064_096_128_160_192_224_256_Datasheet_V5_EN.pdf",
      "note": "8 modules (25.6kWh)."
    },
    {
      "id": "sla_tubular_200ah_string",
      "manufacturer": "Tubular Lead-acid",
      "model": "4x12V 200Ah String",
      "chemistry": "tubular",
      "nominalV": 48.0,
      "capacityAh": 200.0,
      "recommendedDod": 0.6,
      "continuousCharge_A": 40.0,
      "continuousDischarge_A": 120.0,
      "peakDischarge_A": 160.0,
      "peakDuration_s": 5.0,
      "tempMinC": -5.0,
      "tempMaxC": 45.0,
      "datasheetRev": "Project-specific battery bank",
      "datasheetUrl": "",
      "note": "Reference tubular bank block for legacy backup systems."
    }
  ]
}
